[
    {
        "plate": "APS895",
        "make": "INTERNATIONAL",
        "bodyType": "TRACTOR",
        "primaryColour": "RED",
        "vehicleHash": "a+w1GhkH2k8CFT3eQ5olpp29jvzp1nDekN5ZYORHUd0=",
        "registeredConfiguration": "PSV2 - 2 axle SPV - Plant",
        "registeredGvmGcm": "6730/6730",
        "manufacturerGvmGcm": "6730/6730",
        "ctpInsurer": "NRMA",
        "vehicleConditions": {
            "vehicleCondition": [
                "SPV NOT GOODS/PASSENGER CARRYING",
                "SP40 40 KM/H MAXIMUM"
            ]
        },
        "conditions": [
            "SPV NOT GOODS/PASSENGER CARRYING",
            "SP40 40 KM/H MAXIMUM"
        ]
    }
]