[
    {
        "plate": "APV286",
        "make": "ALLIS CHALMERS",
        "bodyType": "TRACTOR",
        "primaryColour": "ORANGE",
        "vehicleHash": "1seeAbWPk8EqgbA7c0cU4opxd6H3T2wbpsCKyVnxXmc=",
        "ctpInsurer": "MAC",
        "vehicleConditions": {
            "vehicleCondition": [
                "SPV NOT GOODS/PASSENGER CARRYING",
                "CTBA CONDITIONS TO BE ASSESSED"
            ]
        },
        "conditions": [
            "SPV NOT GOODS/PASSENGER CARRYING",
            "CTBA CONDITIONS TO BE ASSESSED"
        ]
    }
]