[
    {
        "plate": "ASV302",
        "make": "INTERNATIONAL",
        "bodyType": "TRACTOR",
        "primaryColour": "RED",
        "vehicleHash": "x7B1HTUVNUNwl0io8zQ1Ikn3A4gygEZ00w4cd1doOJA=",
        "registeredGvmGcm": "3500/3500",
        "manufacturerGvmGcm": "3500/3500",
        "ctpInsurer": "QBE",
        "vehicleConditions": {
            "vehicleCondition": [
                "SPV NOT GOODS/PASSENGER CARRYING",
                "SP40 40 KM/H MAXIMUM"
            ]
        },
        "conditions": [
            "SPV NOT GOODS/PASSENGER CARRYING",
            "SP40 40 KM/H MAXIMUM"
        ]
    }
]