[
    {
        "plate": "BPS530",
        "make": "CASE",
        "bodyType": "LAND IMPLEMENT VEHICLE",
        "primaryColour": "RED",
        "vehicleHash": "00QRugUTQIr4YkLhdJpJqF8W7rhBhf08NFgRyJVT5eI=",
        "registeredConfiguration": "PSV2 - 2 axle SPV - Plant",
        "registeredGvmGcm": "10770/",
        "manufacturerGvmGcm": "10770/",
        "ctpInsurer": "MAC",
        "vehicleConditions": {
            "vehicleCondition": [
                "SPV NOT GOODS/PASSENGER CARRYING",
                "CTBA CONDITIONS TO BE ASSESSED"
            ]
        },
        "conditions": [
            "SPV NOT GOODS/PASSENGER CARRYING",
            "CTBA CONDITIONS TO BE ASSESSED"
        ]
    }
]