[
    {
        "plate": "BPV142",
        "make": "FORDSON",
        "bodyType": "TRACTOR",
        "primaryColour": "BLUE",
        "vehicleHash": "56GLsitjRc/LuuXppvgaI1AIGZmH47jdGaT6CLpjQ+k=",
        "registeredGvmGcm": "2000/",
        "manufacturerGvmGcm": "2000/",
        "ctpInsurer": "NRMA",
        "vehicleConditions": {
            "vehicleCondition": "SPV NOT GOODS/PASSENGER CARRYING"
        },
        "conditions": [
            "SPV NOT GOODS/PASSENGER CARRYING"
        ]
    }
]