[
    {
        "plate": "BPV943",
        "make": "FORDSON",
        "bodyType": "TRACTOR",
        "primaryColour": "BLUE",
        "vehicleHash": "M8SPfnrBjXAgwqrFsQWoJgLRqna6dY95Ysp1k5qciic=",
        "registeredGvmGcm": "3710/",
        "manufacturerGvmGcm": "3710/",
        "ctpInsurer": "MAC",
        "vehicleConditions": {
            "vehicleCondition": [
                "SPV NOT GOODS/PASSENGER CARRYING",
                "GO21 GAZETTE - AG VEHICLES UP TO 3M WIDE",
                "SP40 40 KM/H MAXIMUM",
                "TR1 TIME RESTRICTIONS"
            ]
        },
        "conditions": [
            "SPV NOT GOODS/PASSENGER CARRYING",
            "GO21 GAZETTE - AG VEHICLES UP TO 3M WIDE",
            "SP40 40 KM/H MAXIMUM",
            "TR1 TIME RESTRICTIONS"
        ]
    }
]