[
    {
        "plate": "BSP265",
        "make": "HYSTER",
        "bodyType": "FORK-LIFT",
        "primaryColour": "YELLOW",
        "vehicleHash": "ZQmvbQdxAquZCHNCPlq0WC9qSQl9o2zZnhJDADfr1NA=",
        "registeredGvmGcm": "2895/",
        "manufacturerGvmGcm": "2895/",
        "ctpInsurer": "MAC",
        "vehicleConditions": {
            "vehicleCondition": [
                "SPV NOT GOODS/PASSENGER CARRYING",
                "SP40 40 KM/H MAXIMUM"
            ]
        },
        "conditions": [
            "SPV NOT GOODS/PASSENGER CARRYING",
            "SP40 40 KM/H MAXIMUM"
        ]
    }
]