[
    {
        "plate": "BSP828",
        "make": "INTERNATIONAL",
        "bodyType": "TRACTOR",
        "primaryColour": "RED",
        "vehicleHash": "JkNrmEQknN0j3kYoXwxzZ6cO5FXYX3mUeHcR1CuvItw=",
        "registeredGvmGcm": "3200/",
        "manufacturerGvmGcm": "3200/",
        "ctpInsurer": "AAMI",
        "vehicleConditions": {
            "vehicleCondition": [
                "SPV NOT GOODS/PASSENGER CARRYING",
                "SP20 20 KM/H MAXIMUM",
                "TR1 TIME RESTRICTIONS"
            ]
        },
        "expiry": "2026-07-21T00:00:00.000+09:30",
        "conditions": [
            "SPV NOT GOODS/PASSENGER CARRYING",
            "SP20 20 KM/H MAXIMUM",
            "TR1 TIME RESTRICTIONS"
        ]
    }
]