[
    {
        "plate": "BVP016",
        "make": "NISSAN",
        "bodyType": "FORK-LIFT",
        "primaryColour": "RED",
        "vehicleHash": "vzkBhm2m1g+SKmOHBZTgb3iOyl5v85/uTvANozuxnew=",
        "registeredGvmGcm": "4460/",
        "manufacturerGvmGcm": "4460/",
        "ctpInsurer": "MAC",
        "vehicleConditions": {
            "vehicleCondition": [
                "SPV NOT GOODS/PASSENGER CARRYING",
                "SP40 40 KM/H MAXIMUM"
            ]
        },
        "conditions": [
            "SPV NOT GOODS/PASSENGER CARRYING",
            "SP40 40 KM/H MAXIMUM"
        ]
    }
]