[
    {
        "plate": "BVP339",
        "make": "MITSUBISHI",
        "bodyType": "FORK-LIFT",
        "primaryColour": "GREEN",
        "vehicleHash": "8lnKXUdmPq23v8746P80m7xrLUzN1hL0KHN4bNJPn1c=",
        "registeredGvmGcm": "2740/",
        "manufacturerGvmGcm": "2740/",
        "ctpInsurer": "MAC",
        "vehicleConditions": {
            "vehicleCondition": [
                "SPV NOT GOODS/PASSENGER CARRYING",
                "SP40 40 KM/H MAXIMUM"
            ]
        },
        "conditions": [
            "SPV NOT GOODS/PASSENGER CARRYING",
            "SP40 40 KM/H MAXIMUM"
        ]
    }
]