[
    {
        "plate": "BVP492",
        "make": "KOMATSU",
        "bodyType": "FORK-LIFT",
        "primaryColour": "YELLOW",
        "vehicleHash": "uAd4fH+zhZ5f10i0nhO1AESaDs22TrjjwpOOMN6J7qc=",
        "registeredGvmGcm": "2710/2710",
        "manufacturerGvmGcm": "2710/2710",
        "ctpInsurer": "AAMI",
        "vehicleConditions": {
            "vehicleCondition": "SPV NOT GOODS/PASSENGER CARRYING"
        },
        "expiry": "2025-07-05T00:00:00.000+09:30",
        "conditions": [
            "SPV NOT GOODS/PASSENGER CARRYING"
        ]
    }
]