[
    {
        "plate": "BVS760",
        "make": "CHAMBERLAIN",
        "bodyType": "TRACTOR",
        "primaryColour": "YELLOW",
        "vehicleHash": "5DJhXLFA5HLKVRgRIQcusOe29tJy4i3ZgjZRQyyKcHw=",
        "registeredGvmGcm": "3500/",
        "manufacturerGvmGcm": "3500/",
        "ctpInsurer": "MAC",
        "vehicleConditions": {
            "vehicleCondition": [
                "SPV NOT GOODS/PASSENGER CARRYING",
                "SP40 40 KM/H MAXIMUM",
                "TR1 TIME RESTRICTIONS"
            ]
        },
        "conditions": [
            "SPV NOT GOODS/PASSENGER CARRYING",
            "SP40 40 KM/H MAXIMUM",
            "TR1 TIME RESTRICTIONS"
        ]
    }
]