[
    {
        "plate": "BVS988",
        "make": "JOHN DEERE",
        "bodyType": "TRACTOR",
        "primaryColour": "GREEN",
        "vehicleHash": "ws8VWIiyW8jI+eLOJeNLTGp3U4LsMZsCrW9xYve31FM=",
        "registeredConfiguration": "PSV2 - 2 axle SPV - Plant",
        "registeredGvmGcm": "7000/",
        "manufacturerGvmGcm": "7000/",
        "ctpInsurer": "MAC",
        "vehicleConditions": {
            "vehicleCondition": "SPV NOT GOODS/PASSENGER CARRYING"
        },
        "conditions": [
            "SPV NOT GOODS/PASSENGER CARRYING"
        ]
    }
]