[
    {
        "plate": "CSP338",
        "make": "YAMAHA",
        "bodyType": "SOLO",
        "primaryColour": "WHITE",
        "vehicleHash": "A0xY/CRO7ctiS8yvUGH8ZhSunTjokC8YXKVl7rknjCs=",
        "ctpInsurer": "MAC",
        "vehicleConditions": {
            "vehicleCondition": [
                "FMBR BETWEEN FARM BLOCKS",
                "GO17 GAZETTE - 2 WHEEL MOTOR CYCLES FOR AG USE"
            ]
        },
        "conditions": [
            "FMBR BETWEEN FARM BLOCKS",
            "GO17 GAZETTE - 2 WHEEL MOTOR CYCLES FOR AG USE"
        ]
    }
]