[
    {
        "plate": "DPS220",
        "make": "KOMATSU",
        "bodyType": "FORK-LIFT",
        "primaryColour": "YELLOW",
        "vehicleHash": "gVY3uZF48uO756rYo4IL5WZOZeU3NWqOIOs9so3wbh0=",
        "registeredGvmGcm": "3610/3610",
        "manufacturerGvmGcm": "3610/3610",
        "ctpInsurer": "MAC",
        "vehicleConditions": {
            "vehicleCondition": [
                "SPV NOT GOODS/PASSENGER CARRYING",
                "SP40 40 KM/H MAXIMUM"
            ]
        },
        "conditions": [
            "SPV NOT GOODS/PASSENGER CARRYING",
            "SP40 40 KM/H MAXIMUM"
        ]
    }
]