[
    {
        "plate": "DPS423",
        "make": "HYSTER",
        "bodyType": "FORK-LIFT",
        "primaryColour": "YELLOW",
        "vehicleHash": "p/OVNr+oK6/x4bbsYAlqqWprDLYJKZLpLAlmnfJ7Ug4=",
        "registeredGvmGcm": "4000/6300",
        "manufacturerGvmGcm": "4000/6300",
        "ctpInsurer": "QBE",
        "vehicleConditions": {
            "vehicleCondition": "SPV NOT GOODS/PASSENGER CARRYING"
        },
        "expiry": "2025-07-19T00:00:00.000+09:30",
        "conditions": [
            "SPV NOT GOODS/PASSENGER CARRYING"
        ]
    }
]