[
    {
        "plate": "DPS516",
        "make": "JOHN DEERE",
        "bodyType": "TRACTOR",
        "primaryColour": "GREEN",
        "vehicleHash": "wO0tNDiHhtR6j+VR4K/ZraWYgAxZhlUT9ywKpgg3s30=",
        "registeredConfiguration": "PSV2 - 2 axle SPV - Plant",
        "registeredGvmGcm": "7200/7200",
        "manufacturerGvmGcm": "7200/7200",
        "ctpInsurer": "ALLIANZ",
        "vehicleConditions": {
            "vehicleCondition": [
                "SPV NOT GOODS/PASSENGER CARRYING",
                "OS1 AGRICULTURAL GAZETTE",
                "TR1 TIME RESTRICTIONS"
            ]
        },
        "conditions": [
            "SPV NOT GOODS/PASSENGER CARRYING",
            "OS1 AGRICULTURAL GAZETTE",
            "TR1 TIME RESTRICTIONS"
        ]
    }
]