[
    {
        "plate": "DVS324",
        "make": "ZETOR",
        "bodyType": "TRACTOR",
        "primaryColour": "ORANGE",
        "vehicleHash": "bH9q1vN13pn8Tf5w8IPEDUlW2nATDdzDzvLlRi2lOUc=",
        "registeredGvmGcm": "4500/",
        "manufacturerGvmGcm": "4500/",
        "ctpInsurer": "MAC",
        "vehicleConditions": {
            "vehicleCondition": [
                "SPV NOT GOODS/PASSENGER CARRYING",
                "CTBA CONDITIONS TO BE ASSESSED"
            ]
        },
        "conditions": [
            "SPV NOT GOODS/PASSENGER CARRYING",
            "CTBA CONDITIONS TO BE ASSESSED"
        ]
    }
]