[
    {
        "plate": "EPS318",
        "make": "HOMEMADE",
        "bodyType": "INDUSTRIAL TRAILER",
        "primaryColour": "WHITE",
        "vehicleHash": "Fmd//CMlcrt9ASj5MSODacP+iUMZEni8RDSfGXkcpUA=",
        "registeredGvmGcm": "3500/",
        "manufacturerGvmGcm": "3500/",
        "ctpInsurer": "ALLIANZ",
        "vehicleConditions": {
            "vehicleCondition": "SPV NOT GOODS/PASSENGER CARRYING"
        },
        "expiry": "2026-05-28T00:00:00.000+09:30",
        "conditions": [
            "SPV NOT GOODS/PASSENGER CARRYING"
        ]
    }
]