[
    {
        "plate": "EVP995",
        "make": "JOHN DEERE",
        "bodyType": "TRACTOR",
        "primaryColour": "GREEN",
        "vehicleHash": "iRI4rQ8T06yLjbwQDSC2W8cjeeUb9msg4naP9siH7/4=",
        "registeredGvmGcm": "3900/3900",
        "manufacturerGvmGcm": "3900/3900",
        "ctpInsurer": "AAMI",
        "vehicleConditions": {
            "vehicleCondition": "SPV NOT GOODS/PASSENGER CARRYING"
        },
        "expiry": "2025-05-29T00:00:00.000+09:30",
        "conditions": [
            "SPV NOT GOODS/PASSENGER CARRYING"
        ]
    }
]