[
    {
        "plate": "EVS294",
        "make": "HYSTER",
        "bodyType": "FORK-LIFT",
        "primaryColour": "YELLOW",
        "vehicleHash": "mg45IXORCbOdKTTfvhgZBZlwyhG1jIH/jUgg9MifRUU=",
        "registeredConfiguration": "PSV2 - 2 axle SPV - Plant",
        "registeredGvmGcm": "9000/9000",
        "manufacturerGvmGcm": "9000/9000",
        "ctpInsurer": "QBE",
        "vehicleConditions": {
            "vehicleCondition": [
                "SPV NOT GOODS/PASSENGER CARRYING",
                "LO5 ROAD RESTRICTION"
            ]
        },
        "expiry": "2024-11-25T00:00:00.000+10:30",
        "conditions": [
            "SPV NOT GOODS/PASSENGER CARRYING",
            "LO5 ROAD RESTRICTION"
        ]
    }
]