[
    {
        "plate": "FGX335",
        "make": "FORD",
        "bodyType": "SEDAN",
        "primaryColour": "GOLD",
        "vehicleHash": "N3xCwk3qd0+w+cH7qFwFFBdBv6z6O7MEcu74ig/WTPo=",
        "ctpInsurer": "QBE",
        "expiry": "2024-11-05T00:00:00.000+10:30"
    },
    {
        "plate": "FGX335",
        "make": "FORD",
        "bodyType": "SEDAN",
        "primaryColour": "GOLD",
        "vehicleHash": "+Q7aTVOGfFtCKF7bSUWgPR0wDEwhrnK4fW4sspyozZg=",
        "ctpInsurer": "QBE"
    }
]