[
    {
        "plate": "FSP322",
        "make": "NOT LISTED",
        "bodyType": "TRACTOR",
        "primaryColour": "YELLOW",
        "vehicleHash": "8bUdwA5Kth/TfHW4dqEzfpVvEcNb5m++X4W4EKaSJCw=",
        "registeredConfiguration": "PSV3 - 3 axle SPV - Plant",
        "registeredGvmGcm": "7000/",
        "manufacturerGvmGcm": "7000/",
        "ctpInsurer": "MAC",
        "vehicleConditions": {
            "vehicleCondition": [
                "SPV NOT GOODS/PASSENGER CARRYING",
                "GO21 GAZETTE - AG VEHICLES UP TO 3M WIDE",
                "SP40 40 KM/H MAXIMUM",
                "TR1 TIME RESTRICTIONS"
            ]
        },
        "conditions": [
            "SPV NOT GOODS/PASSENGER CARRYING",
            "GO21 GAZETTE - AG VEHICLES UP TO 3M WIDE",
            "SP40 40 KM/H MAXIMUM",
            "TR1 TIME RESTRICTIONS"
        ]
    }
]