[
    {
        "plate": "FVP230",
        "make": "NOT LISTED",
        "bodyType": "FORK-LIFT",
        "primaryColour": "YELLOW",
        "vehicleHash": "XuT9eWKNwFoqJ+uk4WfOuspGWSZ4B2DHoietTeJPZ44=",
        "registeredGvmGcm": "3800/",
        "manufacturerGvmGcm": "3800/",
        "ctpInsurer": "QBE",
        "vehicleConditions": {
            "vehicleCondition": [
                "SPV NOT GOODS/PASSENGER CARRYING",
                "GO9 DEPT OF TRANSPORT DISPENSATION",
                "SP40 40 KM/H MAXIMUM",
                "TR1 TIME RESTRICTIONS"
            ]
        },
        "conditions": [
            "SPV NOT GOODS/PASSENGER CARRYING",
            "GO9 DEPT OF TRANSPORT DISPENSATION",
            "SP40 40 KM/H MAXIMUM",
            "TR1 TIME RESTRICTIONS"
        ]
    }
]