[
    {
        "plate": "FVP611",
        "make": "KOMATSU",
        "bodyType": "FORK-LIFT",
        "primaryColour": "YELLOW",
        "vehicleHash": "hvA9XCR5/gw/bHd9JPJmPYTUqUXI9Q4oQk6rlQHLePw=",
        "registeredGvmGcm": "3220/",
        "manufacturerGvmGcm": "3220/",
        "ctpInsurer": "MAC",
        "vehicleConditions": {
            "vehicleCondition": [
                "SPV NOT GOODS/PASSENGER CARRYING",
                "LO5 ROAD RESTRICTION"
            ]
        },
        "conditions": [
            "SPV NOT GOODS/PASSENGER CARRYING",
            "LO5 ROAD RESTRICTION"
        ]
    }
]