[
    {
        "plate": "GPS257",
        "make": "NEW HOLLAND",
        "bodyType": "TRACTOR",
        "primaryColour": "BLUE",
        "vehicleHash": "pIvHEmI0BcEExBcstoyjQnahWrMuMvb/I8nJf3EY3lc=",
        "registeredGvmGcm": "3600/3600",
        "manufacturerGvmGcm": "3600/3600",
        "ctpInsurer": "NRMA",
        "vehicleConditions": {
            "vehicleCondition": [
                "SPV NOT GOODS/PASSENGER CARRYING",
                "LO5 ROAD RESTRICTION"
            ]
        },
        "expiry": "2025-06-24T00:00:00.000+09:30",
        "conditions": [
            "SPV NOT GOODS/PASSENGER CARRYING",
            "LO5 ROAD RESTRICTION"
        ]
    }
]