[
    {
        "plate": "GVP060",
        "make": "NOT LISTED",
        "bodyType": "INDUSTRIAL TRAILER",
        "primaryColour": "BLACK",
        "vehicleHash": "r4m2v1oce2L4Xifnm3FLmUj+HWm5vL5Ib8PN/j1CYIs=",
        "registeredGvmGcm": "1250/",
        "manufacturerGvmGcm": "1250/",
        "ctpInsurer": "MAC",
        "vehicleConditions": {
            "vehicleCondition": [
                "SPV NOT GOODS/PASSENGER CARRYING",
                "GO25 GAZETTE - CONST/MOVING EQUIP LIGHTING"
            ]
        },
        "conditions": [
            "SPV NOT GOODS/PASSENGER CARRYING",
            "GO25 GAZETTE - CONST/MOVING EQUIP LIGHTING"
        ]
    }
]