[
    {
        "plate": "GVP209",
        "make": "NOT LISTED",
        "bodyType": "FORK-LIFT",
        "primaryColour": "YELLOW",
        "vehicleHash": "/dOMeiguoApb58dNrBKOW3i+1Qi3hXeYOsWnJLtjNw4=",
        "registeredGvmGcm": "3590/",
        "manufacturerGvmGcm": "3590/",
        "ctpInsurer": "MAC",
        "vehicleConditions": {
            "vehicleCondition": [
                "SPV NOT GOODS/PASSENGER CARRYING",
                "SP40 40 KM/H MAXIMUM"
            ]
        },
        "conditions": [
            "SPV NOT GOODS/PASSENGER CARRYING",
            "SP40 40 KM/H MAXIMUM"
        ]
    }
]