[
    {
        "plate": "HPS694",
        "make": "DAVID BROWN",
        "bodyType": "TRACTOR",
        "primaryColour": "WHITE",
        "vehicleHash": "AwV4VZ83K6KgrmyyAAaTY8MA1lIuxqkEXPnLucsQICQ=",
        "registeredGvmGcm": "3120/",
        "manufacturerGvmGcm": "3120/",
        "ctpInsurer": "MAC",
        "vehicleConditions": {
            "vehicleCondition": [
                "SPV NOT GOODS/PASSENGER CARRYING",
                "GO21 GAZETTE - AG VEHICLES UP TO 3M WIDE"
            ]
        },
        "conditions": [
            "SPV NOT GOODS/PASSENGER CARRYING",
            "GO21 GAZETTE - AG VEHICLES UP TO 3M WIDE"
        ]
    }
]