[
    {
        "plate": "HPV029",
        "make": "CASE",
        "bodyType": "TRACTOR",
        "primaryColour": "RED",
        "vehicleHash": "kXZYxM4Ek5ssasVgihRLBogKdpj1+8taoo/9B7FIvk8=",
        "registeredConfiguration": "PSV2 - 2 axle SPV - Plant",
        "registeredGvmGcm": "7178/7178",
        "manufacturerGvmGcm": "7178/7178",
        "ctpInsurer": "MAC",
        "vehicleConditions": {
            "vehicleCondition": [
                "SPV NOT GOODS/PASSENGER CARRYING",
                "OS1 AGRICULTURAL GAZETTE",
                "SP40 40 KM/H MAXIMUM"
            ]
        },
        "conditions": [
            "SPV NOT GOODS/PASSENGER CARRYING",
            "OS1 AGRICULTURAL GAZETTE",
            "SP40 40 KM/H MAXIMUM"
        ]
    }
]