[
    {
        "plate": "HSP107",
        "make": "FORD",
        "bodyType": "TRACTOR",
        "primaryColour": "YELLOW",
        "vehicleHash": "etxEQsyid+bnnqkoXDJaghWW1fbMj1uGx95g4Ykn2jw=",
        "registeredGvmGcm": "2500/",
        "manufacturerGvmGcm": "2500/",
        "ctpInsurer": "MAC",
        "vehicleConditions": {
            "vehicleCondition": [
                "SPV NOT GOODS/PASSENGER CARRYING",
                "SP20 20 KM/H MAXIMUM",
                "TR1 TIME RESTRICTIONS"
            ]
        },
        "conditions": [
            "SPV NOT GOODS/PASSENGER CARRYING",
            "SP20 20 KM/H MAXIMUM",
            "TR1 TIME RESTRICTIONS"
        ]
    }
]