[
    {
        "plate": "HSP267",
        "make": "CASE",
        "bodyType": "TRACTOR",
        "primaryColour": "ORANGE",
        "vehicleHash": "JOhgyWpUK0IVmXVUywMcJVHjl0TmqKcsrXe47VX97TQ=",
        "registeredGvmGcm": "4000/",
        "manufacturerGvmGcm": "4000/",
        "ctpInsurer": "MAC",
        "vehicleConditions": {
            "vehicleCondition": [
                "SPV NOT GOODS/PASSENGER CARRYING",
                "CTBA CONDITIONS TO BE ASSESSED"
            ]
        },
        "conditions": [
            "SPV NOT GOODS/PASSENGER CARRYING",
            "CTBA CONDITIONS TO BE ASSESSED"
        ]
    }
]