[
    {
        "plate": "HVP406",
        "make": "BOMAG",
        "bodyType": "EARTH MOVING VEHICLE",
        "primaryColour": "WHITE",
        "vehicleHash": "YfmiZyQoxf0DL7rwLQxeELUD2eJFRaAwMGosymzX73Y=",
        "registeredConfiguration": "PSV2 - 2 axle SPV - Plant",
        "registeredGvmGcm": "16000/16000",
        "manufacturerGvmGcm": "16000/16000",
        "ctpInsurer": "AAMI",
        "vehicleConditions": {
            "vehicleCondition": [
                "SPV NOT GOODS/PASSENGER CARRYING",
                "LO5 ROAD RESTRICTION"
            ]
        },
        "expiry": "2024-09-30T00:00:00.000+09:30",
        "conditions": [
            "SPV NOT GOODS/PASSENGER CARRYING",
            "LO5 ROAD RESTRICTION"
        ]
    }
]