[
    {
        "plate": "IPS123",
        "make": "JOHN DEERE",
        "bodyType": "QUAD CYCLE",
        "primaryColour": "GREEN",
        "vehicleHash": "VAxz7Q6NEUZgfEcO5bfT1f1y1HlhcukCspNZIMJtOkQ=",
        "ctpInsurer": "MAC",
        "vehicleConditions": {
            "vehicleCondition": [
                "FMBR BETWEEN FARM BLOCKS",
                "GO9 DEPT OF TRANSPORT DISPENSATION"
            ]
        },
        "conditions": [
            "FMBR BETWEEN FARM BLOCKS",
            "GO9 DEPT OF TRANSPORT DISPENSATION"
        ]
    }
]