[
    {
        "plate": "IPS868",
        "make": "CASE",
        "bodyType": "EARTH MOVING VEHICLE",
        "primaryColour": "YELLOW",
        "vehicleHash": "lY/q+JYNlV6wgm6a+oTcGm+mhHalLi+ey9k3SLKzp84=",
        "registeredConfiguration": "PSV2 - 2 axle SPV - Plant",
        "registeredGvmGcm": "5000/",
        "manufacturerGvmGcm": "5000/",
        "ctpInsurer": "MAC",
        "vehicleConditions": {
            "vehicleCondition": [
                "SPV NOT GOODS/PASSENGER CARRYING",
                "CTBA CONDITIONS TO BE ASSESSED"
            ]
        },
        "conditions": [
            "SPV NOT GOODS/PASSENGER CARRYING",
            "CTBA CONDITIONS TO BE ASSESSED"
        ]
    }
]