[
    {
        "plate": "IPV494",
        "make": "HYSTER",
        "bodyType": "FORK-LIFT",
        "primaryColour": "YELLOW",
        "vehicleHash": "uMOiZapyxuI9Y8rz8bTTpa2X9MpvR9IzOcYELoHkwjs=",
        "registeredGvmGcm": "3900/",
        "manufacturerGvmGcm": "3900/",
        "ctpInsurer": "MAC",
        "vehicleConditions": {
            "vehicleCondition": "SPV NOT GOODS/PASSENGER CARRYING"
        },
        "conditions": [
            "SPV NOT GOODS/PASSENGER CARRYING"
        ]
    }
]