[
    {
        "plate": "IPV964",
        "make": "LEYLAND",
        "bodyType": "TRACTOR",
        "primaryColour": "BLUE",
        "vehicleHash": "kKSBFTxBBvny6kuheaLWw33CuajEqO7CobsoPVWW8oc=",
        "registeredGvmGcm": "2500/",
        "manufacturerGvmGcm": "2500/",
        "ctpInsurer": "AAMI",
        "vehicleConditions": {
            "vehicleCondition": "SPV NOT GOODS/PASSENGER CARRYING"
        },
        "conditions": [
            "SPV NOT GOODS/PASSENGER CARRYING"
        ]
    }
]