[
    {
        "plate": "ISP155",
        "make": "CHAMBERLAIN",
        "bodyType": "TRACTOR",
        "primaryColour": "YELLOW",
        "vehicleHash": "8jTx3nR8sVHTDKHkQGhljyNxy2WavCbkyoruBgJ5DC0=",
        "registeredConfiguration": "PSV2 - 2 axle SPV - Plant",
        "registeredGvmGcm": "7200/",
        "manufacturerGvmGcm": "7200/",
        "ctpInsurer": "MAC",
        "vehicleConditions": {
            "vehicleCondition": [
                "SPV NOT GOODS/PASSENGER CARRYING",
                "GO21 GAZETTE - AG VEHICLES UP TO 3M WIDE",
                "SP40 40 KM/H MAXIMUM",
                "TR1 TIME RESTRICTIONS"
            ]
        },
        "conditions": [
            "SPV NOT GOODS/PASSENGER CARRYING",
            "GO21 GAZETTE - AG VEHICLES UP TO 3M WIDE",
            "SP40 40 KM/H MAXIMUM",
            "TR1 TIME RESTRICTIONS"
        ]
    }
]