[
    {
        "plate": "ISP328",
        "make": "NOT LISTED",
        "bodyType": "TRACTOR",
        "primaryColour": "BLUE",
        "vehicleHash": "O/AApBDBez27fNtcQOt17yG2wrNRDefgpgt2TfFhxr8=",
        "registeredGvmGcm": "3000/",
        "manufacturerGvmGcm": "3000/",
        "ctpInsurer": "ALLIANZ",
        "vehicleConditions": {
            "vehicleCondition": [
                "SPV NOT GOODS/PASSENGER CARRYING",
                "SP20 20 KM/H MAXIMUM",
                "TR1 TIME RESTRICTIONS"
            ]
        },
        "conditions": [
            "SPV NOT GOODS/PASSENGER CARRYING",
            "SP20 20 KM/H MAXIMUM",
            "TR1 TIME RESTRICTIONS"
        ]
    }
]