[
    {
        "plate": "ISP690",
        "make": "INTERNATIONAL",
        "bodyType": "TRACTOR",
        "primaryColour": "RED",
        "vehicleHash": "KDTDpAYtEmaTJ+j0N7ZMX/+Da9NJO5MmRPY8e0MxSo8=",
        "registeredGvmGcm": "4010/",
        "manufacturerGvmGcm": "4010/",
        "ctpInsurer": "MAC",
        "vehicleConditions": {
            "vehicleCondition": "SPV NOT GOODS/PASSENGER CARRYING"
        },
        "conditions": [
            "SPV NOT GOODS/PASSENGER CARRYING"
        ]
    }
]