[
    {
        "plate": "IVP086",
        "make": "HYSTER",
        "bodyType": "FORK-LIFT",
        "primaryColour": "YELLOW",
        "vehicleHash": "D26KAOD842sxpT4Ql8LXPLI1E3fpUpa+pBwjd+ckEQs=",
        "registeredGvmGcm": "3150/3150",
        "manufacturerGvmGcm": "3150/3150",
        "ctpInsurer": "AAMI",
        "vehicleConditions": {
            "vehicleCondition": [
                "SPV NOT GOODS/PASSENGER CARRYING",
                "LO5 ROAD RESTRICTION"
            ]
        },
        "conditions": [
            "SPV NOT GOODS/PASSENGER CARRYING",
            "LO5 ROAD RESTRICTION"
        ]
    }
]