[
    {
        "plate": "JSV150",
        "make": "NEW HOLLAND",
        "bodyType": "LAND IMPLEMENT VEHICLE",
        "primaryColour": "YELLOW",
        "vehicleHash": "6g2JSO5mQweU3D7vVceE/Q9fpjEvCElp0lPu4Php6lw=",
        "registeredConfiguration": "PSV2 - 2 axle SPV - Plant",
        "registeredGvmGcm": "7367/",
        "manufacturerGvmGcm": "7367/",
        "ctpInsurer": "MAC",
        "vehicleConditions": {
            "vehicleCondition": "CTBA CONDITIONS TO BE ASSESSED"
        },
        "conditions": [
            "CTBA CONDITIONS TO BE ASSESSED"
        ]
    }
]