[
    {
        "plate": "JSV109",
        "make": "NEW HOLLAND",
        "bodyType": "LAND IMPLEMENT VEHICLE",
        "primaryColour": "YELLOW",
        "vehicleHash": "x1KHsw5w3Qee1jUEUcoH/CBJmIalxzdwbgo/IKm5Cbo=",
        "registeredConfiguration": "PSV2 - 2 axle SPV - Plant",
        "registeredGvmGcm": "9502/",
        "manufacturerGvmGcm": "9502/",
        "ctpInsurer": "MAC",
        "vehicleConditions": {
            "vehicleCondition": [
                "SPV NOT GOODS/PASSENGER CARRYING",
                "CTBA CONDITIONS TO BE ASSESSED"
            ]
        },
        "conditions": [
            "SPV NOT GOODS/PASSENGER CARRYING",
            "CTBA CONDITIONS TO BE ASSESSED"
        ]
    }
]