[
    {
        "plate": "JSV913",
        "make": "HONDA",
        "bodyType": "QUAD CYCLE",
        "primaryColour": "RED",
        "vehicleHash": "jN10PchI2cVY6VsNIsUtF8PctF78TCacBrjaWmh32dI=",
        "ctpInsurer": "MAC",
        "vehicleConditions": {
            "vehicleCondition": [
                "FMBR BETWEEN FARM BLOCKS",
                "GO19 GAZETTE - 3&4 WHEEL AGRICULTURAL BIKE"
            ]
        },
        "conditions": [
            "FMBR BETWEEN FARM BLOCKS",
            "GO19 GAZETTE - 3&4 WHEEL AGRICULTURAL BIKE"
        ]
    }
]