[
    {
        "plate": "JVP533",
        "make": "CASE",
        "bodyType": "EARTH MOVING VEHICLE",
        "primaryColour": "YELLOW",
        "vehicleHash": "x6fX5cZBUx8Za/oaYf+LK7qrha6Z9JbK/YZkl8e1WjU=",
        "registeredGvmGcm": "3500/",
        "manufacturerGvmGcm": "3500/",
        "ctpInsurer": "NRMA",
        "vehicleConditions": {
            "vehicleCondition": [
                "SPV NOT GOODS/PASSENGER CARRYING",
                "LO5 ROAD RESTRICTION"
            ]
        },
        "conditions": [
            "SPV NOT GOODS/PASSENGER CARRYING",
            "LO5 ROAD RESTRICTION"
        ]
    }
]