[
    {
        "plate": "KPS487",
        "make": "NISSAN",
        "bodyType": "FORK-LIFT",
        "primaryColour": "RED",
        "vehicleHash": "pLOUtHi42VldjcrjPpsFd2HqNAI027dvbzgX96OWpds=",
        "registeredConfiguration": "PSV2 - 2 axle SPV - Plant",
        "registeredGvmGcm": "4620/",
        "manufacturerGvmGcm": "4620/",
        "ctpInsurer": "MAC",
        "vehicleConditions": {
            "vehicleCondition": [
                "SPV NOT GOODS/PASSENGER CARRYING",
                "SP40 40 KM/H MAXIMUM"
            ]
        },
        "conditions": [
            "SPV NOT GOODS/PASSENGER CARRYING",
            "SP40 40 KM/H MAXIMUM"
        ]
    }
]