[
    {
        "plate": "KPV782",
        "make": "CASE",
        "bodyType": "TRACTOR",
        "primaryColour": "RED",
        "vehicleHash": "LQ57uq3YQ9QUn7Js71q3AORa5pBcE+/UmiGhKISabu0=",
        "registeredConfiguration": "PSV2 - 2 axle SPV - Plant",
        "registeredGvmGcm": "4506/",
        "manufacturerGvmGcm": "4506/",
        "ctpInsurer": "AAMI",
        "vehicleConditions": {
            "vehicleCondition": [
                "SPV NOT GOODS/PASSENGER CARRYING",
                "GO21 GAZETTE - AG VEHICLES UP TO 3M WIDE",
                "OS1 AGRICULTURAL GAZETTE",
                "SP40 40 KM/H MAXIMUM",
                "TR1 TIME RESTRICTIONS"
            ]
        },
        "expiry": "2026-10-03T00:00:00.000+09:30",
        "conditions": [
            "SPV NOT GOODS/PASSENGER CARRYING",
            "GO21 GAZETTE - AG VEHICLES UP TO 3M WIDE",
            "OS1 AGRICULTURAL GAZETTE",
            "SP40 40 KM/H MAXIMUM",
            "TR1 TIME RESTRICTIONS"
        ]
    }
]