[
    {
        "plate": "KPV980",
        "make": "INTERNATIONAL",
        "bodyType": "LAND IMPLEMENT VEHICLE",
        "primaryColour": "RED",
        "vehicleHash": "atHuuvimn5ISYCp3Nqf/Me6UEKT3cLvKdlyRJVDiT4Q=",
        "registeredConfiguration": "TSV2 - 2 axle SPV - Truck",
        "registeredGvmGcm": "10000/",
        "manufacturerGvmGcm": "10000/",
        "ctpInsurer": "MAC",
        "vehicleConditions": {
            "vehicleCondition": [
                "SPV NOT GOODS/PASSENGER CARRYING",
                "GO21 GAZETTE - AG VEHICLES UP TO 3M WIDE"
            ]
        },
        "conditions": [
            "SPV NOT GOODS/PASSENGER CARRYING",
            "GO21 GAZETTE - AG VEHICLES UP TO 3M WIDE"
        ]
    }
]