[
    {
        "plate": "KSV722",
        "make": "INTERNATIONAL",
        "bodyType": "TRACTOR",
        "primaryColour": "RED",
        "vehicleHash": "n628GkRy1bAt1zl1LcMfP29oqp0NjXHKQfRyVD5U+A4=",
        "ctpInsurer": "MAC",
        "vehicleConditions": {
            "vehicleCondition": [
                "SPV NOT GOODS/PASSENGER CARRYING",
                "SP40 40 KM/H MAXIMUM"
            ]
        },
        "conditions": [
            "SPV NOT GOODS/PASSENGER CARRYING",
            "SP40 40 KM/H MAXIMUM"
        ]
    }
]