[
    {
        "plate": "LPS163",
        "make": "TOYOTA",
        "bodyType": "FORK-LIFT",
        "primaryColour": "ORANGE",
        "vehicleHash": "QIi2mxat+aqGRp01TqMupDJ5wUK9gMhoLhV48msXc/A=",
        "registeredGvmGcm": "3835/",
        "manufacturerGvmGcm": "3835/",
        "ctpInsurer": "MAC",
        "vehicleConditions": {
            "vehicleCondition": "SPV NOT GOODS/PASSENGER CARRYING"
        },
        "conditions": [
            "SPV NOT GOODS/PASSENGER CARRYING"
        ]
    }
]