[
    {
        "plate": "LPS266",
        "make": "NISSAN",
        "bodyType": "FORK-LIFT",
        "primaryColour": "ORANGE",
        "vehicleHash": "1qgH9kaZjow9GsAf7BERerG2u4W3Brhg5PP0o4DuKAU=",
        "registeredGvmGcm": "3770/6270",
        "manufacturerGvmGcm": "3770/6270",
        "ctpInsurer": "MAC",
        "vehicleConditions": {
            "vehicleCondition": [
                "SPV NOT GOODS/PASSENGER CARRYING",
                "SP40 40 KM/H MAXIMUM"
            ]
        },
        "conditions": [
            "SPV NOT GOODS/PASSENGER CARRYING",
            "SP40 40 KM/H MAXIMUM"
        ]
    }
]