[
    {
        "plate": "LPS701",
        "make": "TOYOTA",
        "bodyType": "FORK-LIFT",
        "primaryColour": "ORANGE",
        "vehicleHash": "Z4kCtveosy54wBKCUuwvEr8jc4Fy1+bKIcvJqFM54Gk=",
        "registeredGvmGcm": "3770/",
        "manufacturerGvmGcm": "3770/",
        "ctpInsurer": "MAC",
        "vehicleConditions": {
            "vehicleCondition": [
                "SPV NOT GOODS/PASSENGER CARRYING",
                "SP40 40 KM/H MAXIMUM"
            ]
        },
        "conditions": [
            "SPV NOT GOODS/PASSENGER CARRYING",
            "SP40 40 KM/H MAXIMUM"
        ]
    }
]