[
    {
        "plate": "LVP384",
        "make": "DAEWOO",
        "bodyType": "EARTH MOVING VEHICLE",
        "primaryColour": "YELLOW",
        "vehicleHash": "gfmX9afY/K9kEqKNwkwMXuaTj31TDcPZ96gVj4Xk1EU=",
        "registeredConfiguration": "PSV5 - 5 axle SPV - Plant",
        "registeredGvmGcm": "28800/28800",
        "manufacturerGvmGcm": "28800/28800",
        "ctpInsurer": "MAC",
        "vehicleConditions": {
            "vehicleCondition": [
                "SPV NOT GOODS/PASSENGER CARRYING",
                "LO5A ROAD RESTRICTION GAZETTE"
            ]
        },
        "conditions": [
            "SPV NOT GOODS/PASSENGER CARRYING",
            "LO5A ROAD RESTRICTION GAZETTE"
        ]
    }
]