[
    {
        "plate": "LVP421",
        "make": "NEW HOLLAND",
        "bodyType": "TRACTOR",
        "primaryColour": "BLUE",
        "vehicleHash": "xlkr5h8pz5Y2J7LS/V3aLIoU/zKK0TPfsEZ+yAHC/wg=",
        "registeredConfiguration": "PSV4 - 4 axle SPV - Plant",
        "registeredGvmGcm": "17790/",
        "manufacturerGvmGcm": "17790/",
        "ctpInsurer": "MAC",
        "vehicleConditions": {
            "vehicleCondition": [
                "SPV NOT GOODS/PASSENGER CARRYING",
                "OS1 AGRICULTURAL GAZETTE",
                "SP40 40 KM/H MAXIMUM",
                "TR1 TIME RESTRICTIONS"
            ]
        },
        "conditions": [
            "SPV NOT GOODS/PASSENGER CARRYING",
            "OS1 AGRICULTURAL GAZETTE",
            "SP40 40 KM/H MAXIMUM",
            "TR1 TIME RESTRICTIONS"
        ]
    }
]