[
    {
        "plate": "MPS017",
        "make": "FORD",
        "bodyType": "TRACTOR",
        "primaryColour": "BLUE",
        "vehicleHash": "h2S8XiJXbgKW+F3XXmzyShno0kVXmrx52GC+sBYS2w4=",
        "registeredGvmGcm": "2500/2500",
        "manufacturerGvmGcm": "2500/2500",
        "ctpInsurer": "MAC",
        "vehicleConditions": {
            "vehicleCondition": [
                "SPV NOT GOODS/PASSENGER CARRYING",
                "GO21 GAZETTE - AG VEHICLES UP TO 3M WIDE",
                "OS1 AGRICULTURAL GAZETTE"
            ]
        },
        "conditions": [
            "SPV NOT GOODS/PASSENGER CARRYING",
            "GO21 GAZETTE - AG VEHICLES UP TO 3M WIDE",
            "OS1 AGRICULTURAL GAZETTE"
        ]
    }
]