[
    {
        "plate": "MPS554",
        "make": "CASE",
        "bodyType": "TRACTOR",
        "primaryColour": "RED",
        "vehicleHash": "ndzLt3S1AflVACPbvcoLiZxVskpFlL6CvWT0gFalUlM=",
        "registeredConfiguration": "PSV2 - 2 axle SPV - Plant",
        "registeredGvmGcm": "9160/",
        "manufacturerGvmGcm": "9160/",
        "ctpInsurer": "MAC",
        "vehicleConditions": {
            "vehicleCondition": [
                "SPV NOT GOODS/PASSENGER CARRYING",
                "GO22 AGRICULTURAL VEHICLE AFTER 1996",
                "OS1 AGRICULTURAL GAZETTE"
            ]
        },
        "conditions": [
            "SPV NOT GOODS/PASSENGER CARRYING",
            "GO22 AGRICULTURAL VEHICLE AFTER 1996",
            "OS1 AGRICULTURAL GAZETTE"
        ]
    }
]