[
    {
        "plate": "MPS714",
        "make": "NOT LISTED",
        "bodyType": "FORK-LIFT",
        "primaryColour": "RED",
        "vehicleHash": "HFT++VI3nHL0JMCjoSUL9ZFF1VCoqErTweIIGyQErEc=",
        "registeredConfiguration": "PSV2 - 2 axle SPV - Plant",
        "registeredGvmGcm": "8595/",
        "manufacturerGvmGcm": "8595/",
        "ctpInsurer": "MAC",
        "vehicleConditions": {
            "vehicleCondition": "SP40 40 KM/H MAXIMUM"
        },
        "conditions": [
            "SP40 40 KM/H MAXIMUM"
        ]
    }
]