[
    {
        "plate": "MPV475",
        "make": "FIAT",
        "bodyType": "TRACTOR",
        "primaryColour": "ORANGE",
        "vehicleHash": "hNnxKrm70jl7GNFc8dj69+qvDZ9i797nDy+xFOXy+c8=",
        "registeredGvmGcm": "3370/",
        "manufacturerGvmGcm": "3370/",
        "ctpInsurer": "QBE",
        "vehicleConditions": {
            "vehicleCondition": [
                "SPV NOT GOODS/PASSENGER CARRYING",
                "GO21 GAZETTE - AG VEHICLES UP TO 3M WIDE",
                "SP40 40 KM/H MAXIMUM",
                "TR1 TIME RESTRICTIONS"
            ]
        },
        "expiry": "2026-10-01T00:00:00.000+09:30",
        "conditions": [
            "SPV NOT GOODS/PASSENGER CARRYING",
            "GO21 GAZETTE - AG VEHICLES UP TO 3M WIDE",
            "SP40 40 KM/H MAXIMUM",
            "TR1 TIME RESTRICTIONS"
        ]
    }
]