[
    {
        "plate": "MSP494",
        "make": "INTERNATIONAL",
        "bodyType": "TRACTOR",
        "primaryColour": "RED",
        "vehicleHash": "y8n1vVuXNPLxrovn/jWusk7vdaiiZskPSj7tkZgG6gg=",
        "registeredGvmGcm": "3933/",
        "manufacturerGvmGcm": "3933/",
        "ctpInsurer": "ALLIANZ",
        "vehicleConditions": {
            "vehicleCondition": [
                "SPV NOT GOODS/PASSENGER CARRYING",
                "GO21 GAZETTE - AG VEHICLES UP TO 3M WIDE",
                "SP40 40 KM/H MAXIMUM"
            ]
        },
        "conditions": [
            "SPV NOT GOODS/PASSENGER CARRYING",
            "GO21 GAZETTE - AG VEHICLES UP TO 3M WIDE",
            "SP40 40 KM/H MAXIMUM"
        ]
    }
]