[
    {
        "plate": "MSV276",
        "make": "NOT LISTED",
        "bodyType": "LAND IMPLEMENT VEHICLE",
        "primaryColour": "BLUE",
        "vehicleHash": "D8C4oM3FKslvTmfvd1KLNU/ajuwN/FdwPkoLFHGBTn4=",
        "registeredGvmGcm": "1200/",
        "manufacturerGvmGcm": "1200/",
        "ctpInsurer": "MAC",
        "vehicleConditions": {
            "vehicleCondition": [
                "SPV NOT GOODS/PASSENGER CARRYING",
                "CTBA CONDITIONS TO BE ASSESSED"
            ]
        },
        "conditions": [
            "SPV NOT GOODS/PASSENGER CARRYING",
            "CTBA CONDITIONS TO BE ASSESSED"
        ]
    }
]