[
    {
        "plate": "MVP394",
        "make": "MANITOU",
        "bodyType": "FORK-LIFT",
        "primaryColour": "RED",
        "vehicleHash": "CotLOMAMgaX1poR9XpDD0VH1dh66P/tvRejWyN+FcTU=",
        "registeredGvmGcm": "2272/",
        "manufacturerGvmGcm": "2272/",
        "ctpInsurer": "QBE",
        "vehicleConditions": {
            "vehicleCondition": [
                "SPV NOT GOODS/PASSENGER CARRYING",
                "SP40 40 KM/H MAXIMUM"
            ]
        },
        "expiry": "2027-05-02T00:00:00.000+09:30",
        "conditions": [
            "SPV NOT GOODS/PASSENGER CARRYING",
            "SP40 40 KM/H MAXIMUM"
        ]
    }
]