[
    {
        "plate": "MVP637",
        "make": "CATERPILLAR",
        "bodyType": "EARTH MOVING VEHICLE",
        "primaryColour": "YELLOW",
        "vehicleHash": "tYY1KuDMg/4yHplji31vy04rxKq22CGJovppgR109oo=",
        "registeredGvmGcm": "2589/",
        "manufacturerGvmGcm": "2589/",
        "ctpInsurer": "QBE",
        "vehicleConditions": {
            "vehicleCondition": [
                "SPV NOT GOODS/PASSENGER CARRYING",
                "LO5 ROAD RESTRICTION"
            ]
        },
        "expiry": "2025-06-04T00:00:00.000+09:30",
        "conditions": [
            "SPV NOT GOODS/PASSENGER CARRYING",
            "LO5 ROAD RESTRICTION"
        ]
    }
]