[
    {
        "plate": "NPS367",
        "make": "NEW HOLLAND",
        "bodyType": "TRACTOR",
        "primaryColour": "BLUE",
        "vehicleHash": "Hfg21oOKYHK5v7dXK9pOijnV2KnaPd7o5mClLoV+YtA=",
        "registeredConfiguration": "PSV2 - 2 axle SPV - Plant",
        "registeredGvmGcm": "6000/6000",
        "manufacturerGvmGcm": "6000/6000",
        "ctpInsurer": "MAC",
        "vehicleConditions": {
            "vehicleCondition": [
                "SPV NOT GOODS/PASSENGER CARRYING",
                "CTBA CONDITIONS TO BE ASSESSED"
            ]
        },
        "conditions": [
            "SPV NOT GOODS/PASSENGER CARRYING",
            "CTBA CONDITIONS TO BE ASSESSED"
        ]
    }
]