[
    {
        "plate": "NSP189",
        "make": "FORD",
        "bodyType": "TRACTOR",
        "primaryColour": "BLUE",
        "vehicleHash": "MvethSIfUeBbd5+jV2eMG3VXfoThy0KTWI95pgMj+EE=",
        "registeredGvmGcm": "3500/",
        "manufacturerGvmGcm": "3500/",
        "ctpInsurer": "MAC",
        "vehicleConditions": {
            "vehicleCondition": [
                "SPV NOT GOODS/PASSENGER CARRYING",
                "CTBA CONDITIONS TO BE ASSESSED"
            ]
        },
        "conditions": [
            "SPV NOT GOODS/PASSENGER CARRYING",
            "CTBA CONDITIONS TO BE ASSESSED"
        ]
    }
]