[
    {
        "plate": "NSV499",
        "make": "HYSTER",
        "bodyType": "FORK-LIFT",
        "primaryColour": "YELLOW",
        "vehicleHash": "jZeIHguYQHhSGGxBujxElt+Jk5ACZDglKL+npPcoHu4=",
        "registeredGvmGcm": "3900/3900",
        "manufacturerGvmGcm": "3900/3900",
        "ctpInsurer": "NRMA",
        "vehicleConditions": {
            "vehicleCondition": [
                "SPV NOT GOODS/PASSENGER CARRYING",
                "SP40 40 KM/H MAXIMUM"
            ]
        },
        "conditions": [
            "SPV NOT GOODS/PASSENGER CARRYING",
            "SP40 40 KM/H MAXIMUM"
        ]
    }
]