[
    {
        "plate": "NSV507",
        "make": "NOT LISTED",
        "bodyType": "LAND IMPLEMENT TRAILER",
        "primaryColour": "YELLOW",
        "vehicleHash": "e14xxG37bg+8dSnpxjSoP6sXqnA3CrZiwhVk8j3hbHk=",
        "registeredConfiguration": "OSV1 - 1 axle SPV - Overmass",
        "registeredGvmGcm": "14000/",
        "manufacturerGvmGcm": "14000/",
        "ctpInsurer": "MAC",
        "vehicleConditions": {
            "vehicleCondition": [
                "MSCL RESTRICTED OR LIMITED USE",
                "CTBA CONDITIONS TO BE ASSESSED"
            ]
        },
        "conditions": [
            "MSCL RESTRICTED OR LIMITED USE",
            "CTBA CONDITIONS TO BE ASSESSED"
        ]
    }
]